pyvin_ui-0.1.14.dist-info/licenses/LICENSE
src/__init__.py
src/config.py
src/exceptions.py
src/api/__init__.py
src/api/client.py
src/api/models.py
src/formatting/__init__.py
src/formatting/fields.py
src/formatting/response.py
src/logs/__init__.py
src/logs/logs.py
src/ui/Home.py
src/ui/__init__.py
src/ui/components/__init__.py
src/ui/components/results_table.py
src/ui/pages/VIN_Decoder.py
src/ui/pages/__init__.py
src/validation/__init__.py
src/validation/vin.py
pyvin_ui-0.1.14.dist-info/METADATA
pyvin_ui-0.1.14.dist-info/WHEEL
pyvin_ui-0.1.14.dist-info/top_level.txt
pyvin_ui-0.1.14.dist-info/RECORD
