Metadata-Version: 2.4
Name: pyVIN-UI
Version: 0.1.14
Requires-Python: >=3.10
License-File: LICENSE
Requires-Dist: requests
Requires-Dist: streamlit
Requires-Dist: pydantic>=2.0
Provides-Extra: dev
Requires-Dist: pytest; extra == "dev"
Requires-Dist: pytest-cov; extra == "dev"
Requires-Dist: pytest-mock; extra == "dev"
Requires-Dist: hypothesis; extra == "dev"
Requires-Dist: responses; extra == "dev"
Requires-Dist: ruff; extra == "dev"
Requires-Dist: pre-commit; extra == "dev"
Dynamic: license-file
